simple_mappers
