Metadata-Version: 1.0
Name: simple-mappers
Version: 1.0.2
Summary: A fast and lightweight automatic object to object mapper.
Home-page: UNKNOWN
Author: Luis Felipe Muller
Author-email: luisfmuller@gmail.com
License: UNKNOWN
Keywords: simple_mappers,object-mapper
Platform: UNKNOWN
